Metadata-Version: 2.1
Name: spam-classifier-library
Version: 0.1.3
Summary: A library for spam classification
Home-page: https://github.com/CodeNeuralist/SpamLib
Author: Кирилл
Author-email: totoshkus@gmail.com
Classifier: Development Status :: 3 - Alpha
Classifier: Intended Audience :: Developers
Classifier: License :: OSI Approved :: MIT License
Classifier: Programming Language :: Python :: 3
Classifier: Programming Language :: Python :: 3.7
Classifier: Programming Language :: Python :: 3.8
Classifier: Programming Language :: Python :: 3.9
